{
  "startAreaId": "candle_room",
  "endAreaId": "dusty_cave",
  "connectionList": [
    {
      "areaId": "candle_room",
      "traversables": [
        {
          "toAreaId": "lonely_hideout",
          "traversableName": "Wooden Door",
          "description": "An old wooden door",
          "traversableActionString": "You open the door and go through.",
          "requiredItemIds": []
        }
      ]
    },
    {
      "areaId": "lonely_hideout",
      "traversables": [
        {
          "toAreaId": "candle_room",
          "traversableName": "Metal Door",
          "description": "A shiny metal door",
          "traversableActionString": "The handle of the door is ice cold. You pull it open and go through.",
          "requiredItemIds": []
        },
        {
          "toAreaId": "dusty_cave",
          "traversableName": "Ladder",
          "description": "A wooden ladder",
          "traversableActionString": "The ladder creaks as you begin to ascend. You pull yourself up.",
          "requiredItemIds": ["hidden_key"]
        }
      ]
    },
    {
      "areaId": "dusty_cave",
      "traversables": [
        {
          "toAreaId": "lonely_hideout",
          "traversableName": "Hatch",
          "description": "A hatch in the ground",
          "traversableActionString": "You pull the hatch open and jump down.",
          "requiredItemIds": ["hidden_key"]
        }
      ]
    }
  ]
}